unblockme/__init__.py
unblockme/djikstra_utils.py
unblockme/state_utils.py
unblockme-0.0.3.dist-info/METADATA
unblockme-0.0.3.dist-info/WHEEL
unblockme-0.0.3.dist-info/licenses/LICENSE
unblockme-0.0.3.dist-info/RECORD
